lobo/__init__.py
lobo/main.py
lobo-0.0.4.dist-info/LICENSE
lobo-0.0.4.dist-info/METADATA
lobo-0.0.4.dist-info/WHEEL
lobo-0.0.4.dist-info/entry_points.txt
lobo-0.0.4.dist-info/top_level.txt
lobo-0.0.4.dist-info/RECORD
