Metadata-Version: 2.1
Name: lobo
Version: 0.0.4
Summary: AWS Load Balancer list cli
Home-page: https://github.com/boroivanov/lobo
Author: Borislav Ivanov
Author-email: borogl@gmail.com
License: MIT license
Platform: UNKNOWN
Classifier: Programming Language :: Python
Classifier: Programming Language :: Python :: 3
Classifier: Programming Language :: Python :: 3.3
Classifier: Programming Language :: Python :: 3.4
Classifier: Programming Language :: Python :: 3.5
Classifier: Programming Language :: Python :: 3.6
Classifier: Programming Language :: Python :: 3.7
Classifier: Programming Language :: Python :: 3.8
Classifier: Programming Language :: Python :: 3.9
Requires-Dist: Click (>=6.0)
Requires-Dist: boto3 (>=1.5.33)
Requires-Dist: click-spinner (>=0.1.8)
